<?xml version="1.0" encoding="utf-8"?>
<!DOCTYPE hibernate-mapping PUBLIC "-//Hibernate/Hibernate Mapping DTD 3.0//EN"
"http://www.hibernate.org/dtd/hibernate-mapping-3.0.dtd">
<hibernate-mapping>
	<class name="cn.com.topit.gl.dao.VInventory" table="v_inventory" dynamic-insert="true" dynamic-update="true">
		<id name="id" type="java.lang.Long">
			<column name="id" />
			<generator class="identity" />
		</id>
		<property name="materid" type="java.lang.String">
			<column name="materid" length="50" not-null="true"/>
		</property>
		<property name="type" type="java.lang.Integer">
			<column name="type" not-null="true"/>
		</property>
		<property name="updateTime" type="java.util.Date">
			<column name="update_time" length="500"/>
		</property>
		<property name="quantities" type="java.lang.Double">
			<column name="quantities" precision="18" scale="2" not-null="true"/>
		</property>
		<property name="principal" type="java.lang.String">
			<column name="principal" length="50" not-null="true"/>
		</property>
		<property name="matername" type="java.lang.String">
			<column name="matername" length="50" not-null="true"/>
		</property>
		<property name="matetypeid" type="java.lang.String">
			<column name="matetypeid" length="50" not-null="true"/>
		</property>
	</class>
</hibernate-mapping>
